xorCryptPy/__init__.py
xorCryptPy/xorCryptPy.py
xorCryptPy-1.0.3.dist-info/LICENSE
xorCryptPy-1.0.3.dist-info/METADATA
xorCryptPy-1.0.3.dist-info/WHEEL
xorCryptPy-1.0.3.dist-info/top_level.txt
xorCryptPy-1.0.3.dist-info/RECORD
