Metadata-Version: 2.1
Name: xorCryptPy
Version: 1.0.3
Summary: Simple Python XOR string encryption library
Home-page: https://github.com/ivoilic/xor-crypt-python
Author: Ivo Ilić
Author-email: admin@ivoilic.com
License: UNKNOWN
Platform: UNKNOWN
Classifier: Programming Language :: Python :: 3
Classifier: License :: OSI Approved :: MIT License
Classifier: Operating System :: OS Independent
